DESCRIPTION.rst
MANIFEST.in
setup.py
CellMethy.egg-info/PKG-INFO
CellMethy.egg-info/SOURCES.txt
CellMethy.egg-info/dependency_links.txt
CellMethy.egg-info/top_level.txt
CellMethy/bin/CellMethy.py
data/data_file
data/test.fastq
data/test.sam
images/figure1.png