Metadata-Version: 1.0
Name: CellMethy
Version: 1.2.0
Summary: Identifying focal full methylation of cell subpopulation and inferring fraction
Home-page: https://github.com/pypa/CellMethyproject
Author: Fang Wang
Author-email: wangfang@ems.hrbmu.edu.cn
License: Harbin Medical University, Python Software Foundation License
Keywords: CellMethy setuptools development
Platform: UNKNOWN
Classifier: Development Status :: 3 - Alpha
Classifier: Intended Audience :: Science/Research
Classifier: Topic :: Software Development :: Build Tools
Classifier: License :: OSI Approved :: Python Software Foundation License
Classifier: Operating System :: MacOS :: MacOS X
Classifier: Operating System :: POSIX :: Linux
Classifier: Operating System :: Unix
Classifier: Operating System :: POSIX
Classifier: Programming Language :: Python :: 2.6
Classifier: Programming Language :: Python :: 2.7
